covid19czechia/__init__.py
covid19czechia/mzcr.py
covid19czechia/offline.py
covid19czechia/data/events.json
covid19czechia-0.5.1.dist-info/LICENSE
covid19czechia-0.5.1.dist-info/METADATA
covid19czechia-0.5.1.dist-info/WHEEL
covid19czechia-0.5.1.dist-info/top_level.txt
covid19czechia-0.5.1.dist-info/RECORD
