Metadata-Version: 2.1
Name: covid19czechia
Version: 0.5.1
Summary: Web Scraper for Czechia COVID19 data.
Home-page: https://github.com/martinbenes1996/covid19czechia
Author: Martin Beneš
Author-email: martinbenes1996@gmail.com
License: MPL
Download-URL: https://github.com/martinbenes1996/covid19czechia/archive/0.4.1.tar.gz
Keywords: 2019-nCov,czechia,coronavirus,covid-19,covid-data,covid19-data
Platform: UNKNOWN
Classifier: Development Status :: 4 - Beta
Classifier: Intended Audience :: Science/Research
Classifier: Intended Audience :: Developers
Classifier: Intended Audience :: Other Audience
Classifier: Topic :: Database
Classifier: Topic :: Scientific/Engineering
Classifier: Topic :: Scientific/Engineering :: Information Analysis
Classifier: Topic :: Software Development :: Libraries
Classifier: Topic :: Utilities
Classifier: License :: OSI Approved :: MIT License
Classifier: Programming Language :: Python :: 3
Classifier: Programming Language :: Python :: 3.4
Classifier: Programming Language :: Python :: 3.5
Classifier: Programming Language :: Python :: 3.6
License-File: LICENSE
Requires-Dist: pandas
Requires-Dist: requests
